{
	"configurations" : 
	[
		{
			"directories" : 
			[
				{
					"build" : ".",
					"hasInstallRule" : true,
					"jsonFile" : "directory-.-Release-d3fc0f84e355092e7049.json",
					"minimumCMakeVersion" : 
					{
						"string" : "3.12"
					},
					"projectIndex" : 0,
					"source" : ".",
					"targetIndexes" : 
					[
						0,
						1
					]
				}
			],
			"name" : "Release",
			"projects" : 
			[
				{
					"directoryIndexes" : 
					[
						0
					],
					"name" : "denso_robot_moveit_config",
					"targetIndexes" : 
					[
						0,
						1
					]
				}
			],
			"targets" : 
			[
				{
					"directoryIndex" : 0,
					"id" : "denso_robot_moveit_config_uninstall::@6890427a1f51a3e7e1df",
					"jsonFile" : "target-denso_robot_moveit_config_uninstall-Release-a75ec599c2d882eeee31.json",
					"name" : "denso_robot_moveit_config_uninstall",
					"projectIndex" : 0
				},
				{
					"directoryIndex" : 0,
					"id" : "uninstall::@6890427a1f51a3e7e1df",
					"jsonFile" : "target-uninstall-Release-898fec9c41990807fc02.json",
					"name" : "uninstall",
					"projectIndex" : 0
				}
			]
		}
	],
	"kind" : "codemodel",
	"paths" : 
	{
		"build" : "/home/isg/workspace/denso_ros2_ws/src/build/denso_robot_moveit_config",
		"source" : "/home/isg/workspace/denso_ros2_ws/src/denso_robot_drivers_ros2/denso_robot_moveit_config"
	},
	"version" : 
	{
		"major" : 2,
		"minor" : 3
	}
}
